hyperlane_client/__init__.py
hyperlane_client/discovery.py
hyperlane_client/grpc_client.py
hyperlane_client/orchestrator.py
hyperlane-0.1.0.dist-info/METADATA
hyperlane-0.1.0.dist-info/WHEEL
hyperlane-0.1.0.dist-info/entry_points.txt
hyperlane-0.1.0.dist-info/top_level.txt
hyperlane-0.1.0.dist-info/RECORD
