Metadata-Version: 2.4
Name: hyperlane
Version: 0.1.0
Summary: Distributed GPU inference engine for heterogeneous prosumer hardware
Home-page: https://github.com/yourusername/hyperlane
Author: Hyperlane Team
Author-email: contact@hyperlane.dev
License: MIT
Project-URL: Bug Tracker, https://github.com/yourusername/hyperlane/issues
Project-URL: Documentation, https://github.com/yourusername/hyperlane/blob/main/README.md
Project-URL: Source Code, https://github.com/yourusername/hyperlane
Keywords: distributed-inference,gpu,llm,pipeline-parallelism,inference-engine,model-serving
Classifier: Development Status :: 3 - Alpha
Classifier: Intended Audience :: Developers
Classifier: Intended Audience :: Science/Research
Classifier: License :: OSI Approved :: MIT License
Classifier: Operating System :: OS Independent
Classifier: Programming Language :: Python :: 3
Classifier: Programming Language :: Python :: 3.9
Classifier: Programming Language :: Python :: 3.10
Classifier: Programming Language :: Python :: 3.11
Classifier: Programming Language :: Python :: 3.12
Classifier: Topic :: Scientific/Engineering :: Artificial Intelligence
Classifier: Topic :: System :: Distributed Computing
Requires-Python: >=3.9
Requires-Dist: grpcio>=1.50.0
Requires-Dist: grpcio-tools>=1.50.0
Requires-Dist: zeroconf>=0.60.0
Requires-Dist: protobuf>=3.20.0
Requires-Dist: torch>=2.0.0
Requires-Dist: transformers>=4.30.0
Requires-Dist: onnx>=1.12.0
Requires-Dist: onnxruntime>=1.14.0
Requires-Dist: aiofiles>=23.0.0
Requires-Dist: pytest>=7.0.0
Requires-Dist: black>=22.0.0
Requires-Dist: pylint>=2.15.0
Provides-Extra: gpu
Requires-Dist: onnxruntime-gpu>=1.14.0; extra == "gpu"
Provides-Extra: dev
Requires-Dist: pytest>=7.0.0; extra == "dev"
Requires-Dist: black>=22.0.0; extra == "dev"
Requires-Dist: pylint>=2.15.0; extra == "dev"
Requires-Dist: twine>=4.0.0; extra == "dev"
Dynamic: author
Dynamic: author-email
Dynamic: classifier
Dynamic: description
Dynamic: description-content-type
Dynamic: home-page
Dynamic: keywords
Dynamic: license
Dynamic: project-url
Dynamic: provides-extra
Dynamic: requires-dist
Dynamic: requires-python
Dynamic: summary
